pandas_mssql/__init__.py
pandas_mssql-0.7.dist-info/LICENSE
pandas_mssql-0.7.dist-info/METADATA
pandas_mssql-0.7.dist-info/WHEEL
pandas_mssql-0.7.dist-info/top_level.txt
pandas_mssql-0.7.dist-info/RECORD
